[
  {
    "sku": "C06TPT",
    "name": "Carrinho Fechado Ferramentas C06 3 Gavetas Todo Preto Fercar",
    "quantity": 36.0,
    "revenue": 43218.88,
    "quantity_rank": 12,
    "value_rank": 1,
    "abc_class": "A",
    "avg_price": 1200.52,
    "unit_cost": 707.26,
    "stock": 0.0,
    "gross_profit": 17757.52,
    "gross_margin_percent": 41.09,
    "roi10_max_cpa_total_period": 1775.75,
    "category": "ferramentas",
    "ads_score": 49.13
  },
  {
    "sku": "03080.2050.10",
    "name": "Rodizio Transparente 50MM COM Freio Chapa Giratorio Niquel Soprano",
    "quantity": 238.0,
    "revenue": 2583.82,
    "quantity_rank": 11,
    "value_rank": 76,
    "abc_class": "A",
    "avg_price": 10.86,
    "unit_cost": 4.13,
    "stock": 0.0,
    "gross_profit": 1600.88,
    "gross_margin_percent": 61.96,
    "roi10_max_cpa_total_period": 160.09,
    "category": "rodizios",
    "ads_score": 17.68
  },
  {
    "sku": "16",
    "name": "Caixa Ferramentas Bau Reto N16 80x34x45cm C/ Bandeja Fercar",
    "quantity": 18.0,
    "revenue": 11126.06,
    "quantity_rank": 29,
    "value_rank": 2,
    "abc_class": "A",
    "avg_price": 618.11,
    "unit_cost": 310.26,
    "stock": 0.0,
    "gross_profit": 5541.38,
    "gross_margin_percent": 49.81,
    "roi10_max_cpa_total_period": 554.14,
    "category": "ferramentas",
    "ads_score": 17.01
  },
  {
    "sku": "JFQFCQ77",
    "name": "Cachepot Floreira Flat Vaso 77(32l) 29x77cm Cimento Queimado Japi",
    "quantity": 28.0,
    "revenue": 9486.08,
    "quantity_rank": 17,
    "value_rank": 4,
    "abc_class": "A",
    "avg_price": 338.79,
    "unit_cost": 160.0,
    "stock": 0.0,
    "gross_profit": 5006.08,
    "gross_margin_percent": 52.77,
    "roi10_max_cpa_total_period": 500.61,
    "category": "vasos",
    "ads_score": 16.16
  },
  {
    "sku": "TPJ/AS*BR1",
    "name": "Assento Vaso Sanitário Oval Universal Soft Astra Cor Branco",
    "quantity": 159.0,
    "revenue": 5966.16,
    "quantity_rank": 9,
    "value_rank": 34,
    "abc_class": "A",
    "avg_price": 37.52,
    "unit_cost": 20.0,
    "stock": 0.0,
    "gross_profit": 2786.16,
    "gross_margin_percent": 46.7,
    "roi10_max_cpa_total_period": 278.62,
    "category": "assentos",
    "ads_score": 15.59
  },
  {
    "sku": "TAJ/AS*BR1",
    "name": "Assento Sanitário Almofadado Slim Branco Astra",
    "quantity": 125.0,
    "revenue": 9105.72,
    "quantity_rank": 4,
    "value_rank": 5,
    "abc_class": "A",
    "avg_price": 72.85,
    "unit_cost": 0.0,
    "stock": 0.0,
    "gross_profit": 0.0,
    "gross_margin_percent": 0.0,
    "roi10_max_cpa_total_period": 0.0,
    "category": "assentos",
    "ads_score": 15.36
  },
  {
    "sku": "JVCDB34",
    "name": "Vaso Decor Plantas Cilin Decore 34 (28l) Off White Japi",
    "quantity": 26.0,
    "revenue": 9014.06,
    "quantity_rank": 19,
    "value_rank": 6,
    "abc_class": "A",
    "avg_price": 346.69,
    "unit_cost": 178.83,
    "stock": 0.0,
    "gross_profit": 4364.48,
    "gross_margin_percent": 48.42,
    "roi10_max_cpa_total_period": 436.45,
    "category": "vasos",
    "ads_score": 15.16
  },
  {
    "sku": "C08VM",
    "name": "Carrinho Fechado Ferramentas C08 6 Gavetas Vermelh Cza Fercar",
    "quantity": 7.0,
    "revenue": 10180.65,
    "quantity_rank": 50,
    "value_rank": 3,
    "abc_class": "B",
    "avg_price": 1454.38,
    "unit_cost": 895.13,
    "stock": 0.0,
    "gross_profit": 3914.74,
    "gross_margin_percent": 38.45,
    "roi10_max_cpa_total_period": 391.47,
    "category": "ferramentas",
    "ads_score": 14.38
  },
  {
    "sku": "03080.3050.10",
    "name": "Rodizio Transparente 50MM SEM Freio Chapa Giratorio Niquel Soprano",
    "quantity": 178.0,
    "revenue": 1749.66,
    "quantity_rank": 15,
    "value_rank": 84,
    "abc_class": "A",
    "avg_price": 9.83,
    "unit_cost": 3.57,
    "stock": 0.0,
    "gross_profit": 1114.2,
    "gross_margin_percent": 63.68,
    "roi10_max_cpa_total_period": 111.42,
    "category": "rodizios",
    "ads_score": 14.02
  },
  {
    "sku": "C06PT",
    "name": "Carrinho Fechado Ferramentas C06 3 Gavetas Preto Cinza Fercar Japi",
    "quantity": 6.0,
    "revenue": 7255.8,
    "quantity_rank": 126,
    "value_rank": 55,
    "abc_class": "B",
    "avg_price": 1209.3,
    "unit_cost": 661.11,
    "stock": 0.0,
    "gross_profit": 3289.14,
    "gross_margin_percent": 45.33,
    "roi10_max_cpa_total_period": 328.91,
    "category": "ferramentas",
    "ads_score": 12.09
  },
  {
    "sku": "C08TVM",
    "name": "Carrinho Fechado Ferramentas C08 6 Gavetas Td Vermelho Fercar",
    "quantity": 6.0,
    "revenue": 8238.0,
    "quantity_rank": 119,
    "value_rank": 51,
    "abc_class": "B",
    "avg_price": 1373.0,
    "unit_cost": 890.08,
    "stock": 0.0,
    "gross_profit": 2897.52,
    "gross_margin_percent": 35.17,
    "roi10_max_cpa_total_period": 289.75,
    "category": "ferramentas",
    "ads_score": 12.06
  },
  {
    "sku": "00",
    "name": "Caixa Ferramentas Bau Reto N00 30x13x10 c/ Bandeja Fercar",
    "quantity": 65.0,
    "revenue": 3718.77,
    "quantity_rank": 7,
    "value_rank": 14,
    "abc_class": "A",
    "avg_price": 57.21,
    "unit_cost": 29.55,
    "stock": 0.0,
    "gross_profit": 1798.02,
    "gross_margin_percent": 48.35,
    "roi10_max_cpa_total_period": 179.8,
    "category": "ferramentas",
    "ads_score": 11.8
  },
  {
    "sku": "JFQFPA57",
    "name": "Cachepot Floreira Flat Vaso 57(6l) 15x57cm Preto Ardosi Japi",
    "quantity": 20.0,
    "revenue": 2634.59,
    "quantity_rank": 27,
    "value_rank": 24,
    "abc_class": "A",
    "avg_price": 131.73,
    "unit_cost": 25.52,
    "stock": 0.0,
    "gross_profit": 2124.19,
    "gross_margin_percent": 80.63,
    "roi10_max_cpa_total_period": 212.42,
    "category": "vasos",
    "ads_score": 11.7
  },
  {
    "sku": "JFQFCQ67",
    "name": "Cachepot Floreira Flat Vaso 67(17l) 22x67cm Cimento Queimado Japi",
    "quantity": 23.0,
    "revenue": 5373.52,
    "quantity_rank": 123,
    "value_rank": 88,
    "abc_class": "A",
    "avg_price": 233.63,
    "unit_cost": 114.44,
    "stock": 0.0,
    "gross_profit": 2741.4,
    "gross_margin_percent": 51.02,
    "roi10_max_cpa_total_period": 274.14,
    "category": "vasos",
    "ads_score": 11.63
  },
  {
    "sku": "C08TPT",
    "name": "Carrinho Fechado Ferramentas C08 6 Gavetas Todo Preto Fercar",
    "quantity": 5.0,
    "revenue": 7274.32,
    "quantity_rank": 63,
    "value_rank": 8,
    "abc_class": "B",
    "avg_price": 1454.86,
    "unit_cost": 882.42,
    "stock": 0.0,
    "gross_profit": 2862.22,
    "gross_margin_percent": 39.35,
    "roi10_max_cpa_total_period": 286.22,
    "category": "ferramentas",
    "ads_score": 11.46
  },
  {
    "sku": "C17S",
    "name": "Caixa Descarga Branca Elevada  Regulável 9L Astra",
    "quantity": 20.0,
    "revenue": 1141.32,
    "quantity_rank": 88,
    "value_rank": 112,
    "abc_class": "A",
    "avg_price": 57.07,
    "unit_cost": 5.68,
    "stock": 0.0,
    "gross_profit": 1027.72,
    "gross_margin_percent": 90.05,
    "roi10_max_cpa_total_period": 102.77,
    "category": "outros",
    "ads_score": 11.15
  },
  {
    "sku": "A21",
    "name": "Armário Banheiro A21 28.4x40.8x9.5cm Branco Porta Correr Astra",
    "quantity": 33.0,
    "revenue": 2569.98,
    "quantity_rank": 20,
    "value_rank": 39,
    "abc_class": "A",
    "avg_price": 77.88,
    "unit_cost": 24.71,
    "stock": 0.0,
    "gross_profit": 1754.55,
    "gross_margin_percent": 68.27,
    "roi10_max_cpa_total_period": 175.45,
    "category": "outros",
    "ads_score": 11.05
  },
  {
    "sku": "VED-80-NH",
    "name": "Rodo Vedante Borracha Friso Porta Aluminio 80cm Vivaliz",
    "quantity": 104.0,
    "revenue": 2606.23,
    "quantity_rank": 26,
    "value_rank": 75,
    "abc_class": "A",
    "avg_price": 25.06,
    "unit_cost": 10.0,
    "stock": 0.0,
    "gross_profit": 1566.23,
    "gross_margin_percent": 60.1,
    "roi10_max_cpa_total_period": 156.62,
    "category": "vedantes",
    "ads_score": 10.82
  },
  {
    "sku": "JVCDCQ34",
    "name": "Vaso Decor Plantas Cilin Decore 34 (28l) Cimento Queim Japi",
    "quantity": 6.0,
    "revenue": 2141.32,
    "quantity_rank": 55,
    "value_rank": 36,
    "abc_class": "B",
    "avg_price": 356.89,
    "unit_cost": 77.78,
    "stock": 0.0,
    "gross_profit": 1674.64,
    "gross_margin_percent": 78.21,
    "roi10_max_cpa_total_period": 167.46,
    "category": "vasos",
    "ads_score": 10.26
  },
  {
    "sku": "KIT4R-SOPRAO",
    "name": "KIT4R-SOPRÃO",
    "quantity": 2.0,
    "revenue": 90.0,
    "quantity_rank": 112,
    "value_rank": 116,
    "abc_class": "C",
    "avg_price": 45.0,
    "unit_cost": 2.35,
    "stock": 0.0,
    "gross_profit": 85.3,
    "gross_margin_percent": 94.78,
    "roi10_max_cpa_total_period": 8.53,
    "category": "outros",
    "ads_score": 9.67
  },
  {
    "sku": "JVAQMA44",
    "name": "Vaso Decorativo Plantas Antique 44 (70l) Macchiato Japi",
    "quantity": 10.0,
    "revenue": 3890.72,
    "quantity_rank": 36,
    "value_rank": 13,
    "abc_class": "B",
    "avg_price": 389.07,
    "unit_cost": 185.24,
    "stock": 0.0,
    "gross_profit": 2038.32,
    "gross_margin_percent": 52.39,
    "roi10_max_cpa_total_period": 203.83,
    "category": "vasos",
    "ads_score": 9.63
  },
  {
    "sku": "COM2",
    "name": "Comedouro Automatico  Regulavel Caes Gatosv5 Kg Fercar",
    "quantity": 24.0,
    "revenue": 3108.72,
    "quantity_rank": 93,
    "value_rank": 80,
    "abc_class": "A",
    "avg_price": 129.53,
    "unit_cost": 61.94,
    "stock": 0.0,
    "gross_profit": 1622.16,
    "gross_margin_percent": 52.18,
    "roi10_max_cpa_total_period": 162.22,
    "category": "pet",
    "ads_score": 9.53
  },
  {
    "sku": "JFQFAC67",
    "name": "Cachepot Floreira Flat Vaso 67(17l) 22x67cm Aco Corten Japi",
    "quantity": 12.0,
    "revenue": 2692.49,
    "quantity_rank": 33,
    "value_rank": 23,
    "abc_class": "B",
    "avg_price": 224.37,
    "unit_cost": 85.07,
    "stock": 0.0,
    "gross_profit": 1671.65,
    "gross_margin_percent": 62.09,
    "roi10_max_cpa_total_period": 167.16,
    "category": "vasos",
    "ads_score": 9.5
  },
  {
    "sku": "JVAQAC55",
    "name": "Vaso Decorativo Plantas Antique 55 (75l) Aço Corten Japi",
    "quantity": 6.0,
    "revenue": 2922.0,
    "quantity_rank": 58,
    "value_rank": 20,
    "abc_class": "B",
    "avg_price": 487.0,
    "unit_cost": 191.09,
    "stock": 0.0,
    "gross_profit": 1775.46,
    "gross_margin_percent": 60.76,
    "roi10_max_cpa_total_period": 177.55,
    "category": "vasos",
    "ads_score": 9.3
  },
  {
    "sku": "JFQFE77",
    "name": "Cachepot Floreira Flat Vaso 77(32l) 29x77cm Chumbo Japi",
    "quantity": 8.0,
    "revenue": 2953.14,
    "quantity_rank": 42,
    "value_rank": 18,
    "abc_class": "B",
    "avg_price": 369.14,
    "unit_cost": 155.48,
    "stock": 0.0,
    "gross_profit": 1709.3,
    "gross_margin_percent": 57.88,
    "roi10_max_cpa_total_period": 170.93,
    "category": "vasos",
    "ads_score": 9.14
  },
  {
    "sku": "COM3",
    "name": "Comedouro Automatico Regulavel Caes Gatos 10 Kg Fercar",
    "quantity": 13.0,
    "revenue": 2520.88,
    "quantity_rank": 32,
    "value_rank": 31,
    "abc_class": "B",
    "avg_price": 193.91,
    "unit_cost": 81.8,
    "stock": 0.0,
    "gross_profit": 1457.48,
    "gross_margin_percent": 57.82,
    "roi10_max_cpa_total_period": 145.75,
    "category": "pet",
    "ads_score": 8.95
  },
  {
    "sku": "JVCDAC34",
    "name": "Vaso Decor Plantas Cilin Decore 34 (28l) Aço Corten Japi",
    "quantity": 9.0,
    "revenue": 3280.82,
    "quantity_rank": 37,
    "value_rank": 15,
    "abc_class": "B",
    "avg_price": 364.54,
    "unit_cost": 180.78,
    "stock": 0.0,
    "gross_profit": 1653.8,
    "gross_margin_percent": 50.41,
    "roi10_max_cpa_total_period": 165.38,
    "category": "vasos",
    "ads_score": 8.77
  },
  {
    "sku": "JFQFAC77",
    "name": "Cachepot Floreira Flat Vaso 77(32l) 29x77cm Aco Corten Japi",
    "quantity": 8.0,
    "revenue": 2838.08,
    "quantity_rank": 40,
    "value_rank": 22,
    "abc_class": "B",
    "avg_price": 354.76,
    "unit_cost": 160.0,
    "stock": 0.0,
    "gross_profit": 1558.08,
    "gross_margin_percent": 54.9,
    "roi10_max_cpa_total_period": 155.81,
    "category": "vasos",
    "ads_score": 8.73
  },
  {
    "sku": "14",
    "name": "Caixa Ferramentas Bau Reto N14 60x30x25cm C/ Bandeja Fercar",
    "quantity": 8.0,
    "revenue": 2603.42,
    "quantity_rank": 47,
    "value_rank": 27,
    "abc_class": "B",
    "avg_price": 325.43,
    "unit_cost": 141.69,
    "stock": 0.0,
    "gross_profit": 1469.9,
    "gross_margin_percent": 56.46,
    "roi10_max_cpa_total_period": 146.99,
    "category": "ferramentas",
    "ads_score": 8.65
  },
  {
    "sku": "JVAQAC44",
    "name": "Vaso Decorativo Plantas Antique 44 (70l) Aco Corten Japi",
    "quantity": 6.0,
    "revenue": 2577.5,
    "quantity_rank": 60,
    "value_rank": 29,
    "abc_class": "B",
    "avg_price": 429.58,
    "unit_cost": 185.24,
    "stock": 0.0,
    "gross_profit": 1466.06,
    "gross_margin_percent": 56.88,
    "roi10_max_cpa_total_period": 146.61,
    "category": "vasos",
    "ads_score": 8.57
  },
  {
    "sku": "JFQFE57",
    "name": "Cachepot Floreira Flat Vaso 57(6l) 15x57cm Chumbo Japi",
    "quantity": 1.0,
    "revenue": 198.97,
    "quantity_rank": 132,
    "value_rank": 97,
    "abc_class": "C",
    "avg_price": 198.97,
    "unit_cost": 37.92,
    "stock": 0.0,
    "gross_profit": 161.05,
    "gross_margin_percent": 80.94,
    "roi10_max_cpa_total_period": 16.11,
    "category": "vasos",
    "ads_score": 8.34
  },
  {
    "sku": "JFQFCQ57",
    "name": "Cachepot Floreira Flat Vaso 57 (6l)15x57cm Cimento Quei Japi",
    "quantity": 22.0,
    "revenue": 2610.45,
    "quantity_rank": 24,
    "value_rank": 25,
    "abc_class": "A",
    "avg_price": 118.66,
    "unit_cost": 63.8,
    "stock": 0.0,
    "gross_profit": 1206.85,
    "gross_margin_percent": 46.23,
    "roi10_max_cpa_total_period": 120.68,
    "category": "vasos",
    "ads_score": 8.33
  },
  {
    "sku": "JVAQMA55",
    "name": "Vaso Antique 55 75L Macchiato Japi Brown",
    "quantity": 4.0,
    "revenue": 1967.68,
    "quantity_rank": 73,
    "value_rank": 38,
    "abc_class": "B",
    "avg_price": 491.92,
    "unit_cost": 192.2,
    "stock": 0.0,
    "gross_profit": 1198.88,
    "gross_margin_percent": 60.93,
    "roi10_max_cpa_total_period": 119.89,
    "category": "vasos",
    "ads_score": 8.26
  },
  {
    "sku": "JVCDPA34",
    "name": "Vaso Cilíndrico Decore 34 28L Preto Ardósia Japi",
    "quantity": 6.0,
    "revenue": 1759.22,
    "quantity_rank": 59,
    "value_rank": 42,
    "abc_class": "B",
    "avg_price": 293.2,
    "unit_cost": 120.52,
    "stock": 0.0,
    "gross_profit": 1036.1,
    "gross_margin_percent": 58.9,
    "roi10_max_cpa_total_period": 103.61,
    "category": "vasos",
    "ads_score": 7.95
  },
  {
    "sku": "C08PT",
    "name": "Carrinho Fechado Ferramentas C08 6 Gavetas Preto Cinza Fercar",
    "quantity": 3.0,
    "revenue": 4136.51,
    "quantity_rank": 81,
    "value_rank": 12,
    "abc_class": "C",
    "avg_price": 1378.84,
    "unit_cost": 891.99,
    "stock": 0.0,
    "gross_profit": 1460.54,
    "gross_margin_percent": 35.31,
    "roi10_max_cpa_total_period": 146.05,
    "category": "ferramentas",
    "ads_score": 7.82
  },
  {
    "sku": "JVAQMA56",
    "name": "Vaso Decorativo Plantas Antique 56 (46l) Macchiato Japi",
    "quantity": 3.0,
    "revenue": 1158.75,
    "quantity_rank": 82,
    "value_rank": 56,
    "abc_class": "C",
    "avg_price": 386.25,
    "unit_cost": 138.18,
    "stock": 0.0,
    "gross_profit": 744.21,
    "gross_margin_percent": 64.23,
    "roi10_max_cpa_total_period": 74.42,
    "category": "vasos",
    "ads_score": 7.73
  },
  {
    "sku": "JFQFAC57",
    "name": "Cachepot Floreira Flat Vaso 57(6l) 15x57cm Aço Corten Japi",
    "quantity": 12.0,
    "revenue": 1659.52,
    "quantity_rank": 35,
    "value_rank": 45,
    "abc_class": "B",
    "avg_price": 138.29,
    "unit_cost": 64.06,
    "stock": 0.0,
    "gross_profit": 890.8,
    "gross_margin_percent": 53.68,
    "roi10_max_cpa_total_period": 89.08,
    "category": "vasos",
    "ads_score": 7.63
  },
  {
    "sku": "13",
    "name": "Caixa Ferramentas Bau Reto N13 50x25x22 C/ Bandeja Fercar",
    "quantity": 8.0,
    "revenue": 1698.19,
    "quantity_rank": 45,
    "value_rank": 44,
    "abc_class": "B",
    "avg_price": 212.27,
    "unit_cost": 95.46,
    "stock": 0.0,
    "gross_profit": 934.51,
    "gross_margin_percent": 55.03,
    "roi10_max_cpa_total_period": 93.45,
    "category": "ferramentas",
    "ads_score": 7.6
  },
  {
    "sku": "1C7Q-LKUU-0BA3",
    "name": "Rodízio Transparente 035mm Freio Chapa Giratória Soprano",
    "quantity": 63.0,
    "revenue": 615.5,
    "quantity_rank": 8,
    "value_rank": 68,
    "abc_class": "A",
    "avg_price": 9.77,
    "unit_cost": 3.12,
    "stock": 0.0,
    "gross_profit": 418.94,
    "gross_margin_percent": 68.06,
    "roi10_max_cpa_total_period": 41.89,
    "category": "rodizios",
    "ads_score": 7.57
  },
  {
    "sku": "COM1",
    "name": "Comedouro Automatico  Regulavel Caes Gatos 2,5 Kg Fercar",
    "quantity": 24.0,
    "revenue": 1810.7,
    "quantity_rank": 121,
    "value_rank": 120,
    "abc_class": "A",
    "avg_price": 75.45,
    "unit_cost": 41.14,
    "stock": 0.0,
    "gross_profit": 823.34,
    "gross_margin_percent": 45.47,
    "roi10_max_cpa_total_period": 82.33,
    "category": "pet",
    "ads_score": 7.56
  },
  {
    "sku": "RODOVED100",
    "name": "Rodo Vedante Borracha Friso Porta Aluminio 100cm Vivaliz",
    "quantity": 47.0,
    "revenue": 1426.18,
    "quantity_rank": 48,
    "value_rank": 100,
    "abc_class": "A",
    "avg_price": 30.34,
    "unit_cost": 10.0,
    "stock": 0.0,
    "gross_profit": 956.18,
    "gross_margin_percent": 67.04,
    "roi10_max_cpa_total_period": 95.62,
    "category": "vedantes",
    "ads_score": 7.48
  },
  {
    "sku": "ARM-08",
    "name": "Armário Ferramentas Duas Portas ARM-08 Fercar",
    "quantity": 4.0,
    "revenue": 2081.56,
    "quantity_rank": 75,
    "value_rank": 37,
    "abc_class": "B",
    "avg_price": 520.39,
    "unit_cost": 263.11,
    "stock": 0.0,
    "gross_profit": 1029.12,
    "gross_margin_percent": 49.44,
    "roi10_max_cpa_total_period": 102.91,
    "category": "ferramentas",
    "ads_score": 7.23
  },
  {
    "sku": "ADSABBR",
    "name": "Saboneteira Comadesivo Astra Branco Fixação Rapida - Branco",
    "quantity": 7.0,
    "revenue": 208.49,
    "quantity_rank": 53,
    "value_rank": 96,
    "abc_class": "B",
    "avg_price": 29.78,
    "unit_cost": 1.2,
    "stock": 0.0,
    "gross_profit": 200.09,
    "gross_margin_percent": 95.97,
    "roi10_max_cpa_total_period": 20.01,
    "category": "outros",
    "ads_score": 7.16
  },
  {
    "sku": "JFUBCQ10",
    "name": "Cachepot Floreira Flat Vaso Urbe 100 (119L) Cimento Queimado Japi",
    "quantity": 2.0,
    "revenue": 1341.28,
    "quantity_rank": 100,
    "value_rank": 49,
    "abc_class": "C",
    "avg_price": 670.64,
    "unit_cost": 299.79,
    "stock": 0.0,
    "gross_profit": 741.7,
    "gross_margin_percent": 55.3,
    "roi10_max_cpa_total_period": 74.17,
    "category": "vasos",
    "ads_score": 6.97
  },
  {
    "sku": "CAD-3050-FBACD",
    "name": "Cadeado Haste Longa Latão- Papaiz 30/50",
    "quantity": 4.0,
    "revenue": 218.25,
    "quantity_rank": 74,
    "value_rank": 95,
    "abc_class": "B",
    "avg_price": 54.56,
    "unit_cost": 18.97,
    "stock": 0.0,
    "gross_profit": 142.37,
    "gross_margin_percent": 65.23,
    "roi10_max_cpa_total_period": 14.24,
    "category": "outros",
    "ads_score": 6.94
  },
  {
    "sku": "15",
    "name": "Caixa Ferramentas Bau Reto N15 37x70x28cm Bandeja Fercar",
    "quantity": 2.0,
    "revenue": 783.84,
    "quantity_rank": 99,
    "value_rank": 60,
    "abc_class": "C",
    "avg_price": 391.92,
    "unit_cost": 154.93,
    "stock": 0.0,
    "gross_profit": 473.98,
    "gross_margin_percent": 60.47,
    "roi10_max_cpa_total_period": 47.4,
    "category": "ferramentas",
    "ads_score": 6.93
  },
  {
    "sku": "C08AZ",
    "name": "Carrinho Fechado Ferramentas C08 6 Gavetas Azul Cinza Fercar",
    "quantity": 2.0,
    "revenue": 2934.15,
    "quantity_rank": 107,
    "value_rank": 19,
    "abc_class": "C",
    "avg_price": 1467.08,
    "unit_cost": 900.0,
    "stock": 0.0,
    "gross_profit": 1134.15,
    "gross_margin_percent": 38.65,
    "roi10_max_cpa_total_period": 113.42,
    "category": "ferramentas",
    "ads_score": 6.9
  },
  {
    "sku": "JVCDE34",
    "name": "Vaso Decor Plantas Cilin Decore 34 (28l) Chumbo Japi",
    "quantity": 6.0,
    "revenue": 1941.5,
    "quantity_rank": 62,
    "value_rank": 40,
    "abc_class": "B",
    "avg_price": 323.58,
    "unit_cost": 174.73,
    "stock": 0.0,
    "gross_profit": 893.12,
    "gross_margin_percent": 46.0,
    "roi10_max_cpa_total_period": 89.31,
    "category": "vasos",
    "ads_score": 6.84
  },
  {
    "sku": "TTH-K*BCO-01",
    "name": "Assento Sanitário Almofadado Thema/Hawaii/Arezzon/Valentina Branco Astra",
    "quantity": 21.0,
    "revenue": 2898.0,
    "quantity_rank": 25,
    "value_rank": 21,
    "abc_class": "A",
    "avg_price": 138.0,
    "unit_cost": 99.99,
    "stock": 0.0,
    "gross_profit": 798.21,
    "gross_margin_percent": 27.54,
    "roi10_max_cpa_total_period": 79.82,
    "category": "assentos",
    "ads_score": 6.7
  },
  {
    "sku": "C06AZ",
    "name": "Carrinho Fechado Ferramentas C06 3 Gavetas Azul Cinza Fercar",
    "quantity": 2.0,
    "revenue": 2389.92,
    "quantity_rank": 98,
    "value_rank": 33,
    "abc_class": "C",
    "avg_price": 1194.96,
    "unit_cost": 704.95,
    "stock": 0.0,
    "gross_profit": 980.02,
    "gross_margin_percent": 41.01,
    "roi10_max_cpa_total_period": 98.0,
    "category": "ferramentas",
    "ads_score": 6.59
  },
  {
    "sku": "1C7Q-LKUT-YLKI",
    "name": "Rodízio Transparente 035mm Sem Freio Chapa Giratória Soprano",
    "quantity": 2.0,
    "revenue": 22.5,
    "quantity_rank": 103,
    "value_rank": 142,
    "abc_class": "C",
    "avg_price": 11.25,
    "unit_cost": 0.78,
    "stock": 0.0,
    "gross_profit": 20.94,
    "gross_margin_percent": 93.07,
    "roi10_max_cpa_total_period": 2.09,
    "category": "rodizios",
    "ads_score": 6.43
  },
  {
    "sku": "23050",
    "name": "Jogo Cinta Catraca Amarração 25mm X 4,6m 800kg Aquatools",
    "quantity": 2.0,
    "revenue": 84.55,
    "quantity_rank": 111,
    "value_rank": 118,
    "abc_class": "C",
    "avg_price": 42.27,
    "unit_cost": 17.0,
    "stock": 0.0,
    "gross_profit": 50.55,
    "gross_margin_percent": 59.79,
    "roi10_max_cpa_total_period": 5.05,
    "category": "outros",
    "ads_score": 6.16
  },
  {
    "sku": "COR5",
    "name": "Caixa Correio Vertical Trava para Grade/Embutir COR5 Fercar",
    "quantity": 5.0,
    "revenue": 393.6,
    "quantity_rank": 65,
    "value_rank": 78,
    "abc_class": "B",
    "avg_price": 78.72,
    "unit_cost": 35.89,
    "stock": 0.0,
    "gross_profit": 214.15,
    "gross_margin_percent": 54.41,
    "roi10_max_cpa_total_period": 21.42,
    "category": "outros",
    "ads_score": 6.08
  },
  {
    "sku": "COM4",
    "name": "Comedouro Aves Pássaros com Fruteira COM4 Fercar",
    "quantity": 7.0,
    "revenue": 571.9,
    "quantity_rank": 49,
    "value_rank": 71,
    "abc_class": "B",
    "avg_price": 81.7,
    "unit_cost": 40.11,
    "stock": 0.0,
    "gross_profit": 291.13,
    "gross_margin_percent": 50.91,
    "roi10_max_cpa_total_period": 29.11,
    "category": "pet",
    "ads_score": 6.01
  },
  {
    "sku": "JVCDB33",
    "name": "Vaso Decor Plantas Cilin Decore 33 (16l) Off White Japi",
    "quantity": 2.0,
    "revenue": 647.2,
    "quantity_rank": 102,
    "value_rank": 66,
    "abc_class": "C",
    "avg_price": 323.6,
    "unit_cost": 155.0,
    "stock": 0.0,
    "gross_profit": 337.2,
    "gross_margin_percent": 52.1,
    "roi10_max_cpa_total_period": 33.72,
    "category": "vasos",
    "ads_score": 5.96
  },
  {
    "sku": "C06TVM",
    "name": "Carrinho Fechado Ferramentas C06 3 Gavetas Td Vermelho Fercar",
    "quantity": 1.0,
    "revenue": 1299.0,
    "quantity_rank": 146,
    "value_rank": 50,
    "abc_class": "C",
    "avg_price": 1299.0,
    "unit_cost": 700.0,
    "stock": 0.0,
    "gross_profit": 599.0,
    "gross_margin_percent": 46.11,
    "roi10_max_cpa_total_period": 59.9,
    "category": "ferramentas",
    "ads_score": 5.96
  },
  {
    "sku": "CR50",
    "name": "Cadeado Papaiz 50mm Latão 2 Chaves Dourado",
    "quantity": 4.0,
    "revenue": 312.0,
    "quantity_rank": 72,
    "value_rank": 83,
    "abc_class": "B",
    "avg_price": 78.0,
    "unit_cost": 36.0,
    "stock": 0.0,
    "gross_profit": 168.0,
    "gross_margin_percent": 53.85,
    "roi10_max_cpa_total_period": 16.8,
    "category": "outros",
    "ads_score": 5.9
  },
  {
    "sku": "COR2",
    "name": "Caixa Correios Embutir 33x26x11 Cm COR2 Fercar",
    "quantity": 2.0,
    "revenue": 193.8,
    "quantity_rank": 96,
    "value_rank": 99,
    "abc_class": "C",
    "avg_price": 96.9,
    "unit_cost": 43.08,
    "stock": 0.0,
    "gross_profit": 107.64,
    "gross_margin_percent": 55.54,
    "roi10_max_cpa_total_period": 10.76,
    "category": "outros",
    "ads_score": 5.85
  },
  {
    "sku": "N05",
    "name": "Caixa Ferramentas Sanfonada 3 Gavetas Vermelha 50x20x17cm N05 Fercar",
    "quantity": 2.0,
    "revenue": 314.0,
    "quantity_rank": 106,
    "value_rank": 82,
    "abc_class": "C",
    "avg_price": 157.0,
    "unit_cost": 74.0,
    "stock": 0.0,
    "gross_profit": 166.0,
    "gross_margin_percent": 52.87,
    "roi10_max_cpa_total_period": 16.6,
    "category": "ferramentas",
    "ads_score": 5.7
  },
  {
    "sku": "03S",
    "name": "Caixa Ferramentas Sanfonada 3 Gavetas 20x30x17cm N03S Fercar",
    "quantity": 2.0,
    "revenue": 242.5,
    "quantity_rank": 97,
    "value_rank": 89,
    "abc_class": "C",
    "avg_price": 121.25,
    "unit_cost": 56.38,
    "stock": 0.0,
    "gross_profit": 129.74,
    "gross_margin_percent": 53.5,
    "roi10_max_cpa_total_period": 12.97,
    "category": "ferramentas",
    "ads_score": 5.69
  },
  {
    "sku": "7323",
    "name": "Gancho/Armador Rede De Embutir Inox  Cromado 7323 Aliança",
    "quantity": 8.0,
    "revenue": 627.28,
    "quantity_rank": 77,
    "value_rank": 91,
    "abc_class": "B",
    "avg_price": 78.41,
    "unit_cost": 41.97,
    "stock": 0.0,
    "gross_profit": 291.52,
    "gross_margin_percent": 46.47,
    "roi10_max_cpa_total_period": 29.15,
    "category": "outros",
    "ads_score": 5.67
  },
  {
    "sku": "9",
    "name": "Caixa Ferramentas Sanfonada 7 Gavetas 50x20x25 cm N09 Fercar",
    "quantity": 3.0,
    "revenue": 720.0,
    "quantity_rank": 80,
    "value_rank": 63,
    "abc_class": "B",
    "avg_price": 240.0,
    "unit_cost": 127.0,
    "stock": 0.0,
    "gross_profit": 339.0,
    "gross_margin_percent": 47.08,
    "roi10_max_cpa_total_period": 33.9,
    "category": "ferramentas",
    "ads_score": 5.58
  },
  {
    "sku": "178970678530",
    "name": "Cofrinho Infantil Segredo Senha Moedas Cédulas Fercar",
    "quantity": 29.0,
    "revenue": 760.46,
    "quantity_rank": 16,
    "value_rank": 62,
    "abc_class": "A",
    "avg_price": 26.22,
    "unit_cost": 9.96,
    "stock": 0.0,
    "gross_profit": 471.62,
    "gross_margin_percent": 62.02,
    "roi10_max_cpa_total_period": 47.16,
    "category": "outros",
    "ads_score": 5.41
  },
  {
    "sku": "C08BR",
    "name": "Carrinho Fechado Ferramentas C08 6 Gavetas Branco Fercar",
    "quantity": 1.0,
    "revenue": 1462.23,
    "quantity_rank": 140,
    "value_rank": 47,
    "abc_class": "C",
    "avg_price": 1462.23,
    "unit_cost": 895.12,
    "stock": 0.0,
    "gross_profit": 567.11,
    "gross_margin_percent": 38.78,
    "roi10_max_cpa_total_period": 56.71,
    "category": "ferramentas",
    "ads_score": 5.39
  },
  {
    "sku": "JVTBPA32",
    "name": "Vaso Decorativo Planta Tribo Japi 43x32cm 32 Preto Ardósia",
    "quantity": 3.0,
    "revenue": 426.54,
    "quantity_rank": 87,
    "value_rank": 77,
    "abc_class": "C",
    "avg_price": 142.18,
    "unit_cost": 75.0,
    "stock": 0.0,
    "gross_profit": 201.54,
    "gross_margin_percent": 47.25,
    "roi10_max_cpa_total_period": 20.15,
    "category": "vasos",
    "ads_score": 5.3
  },
  {
    "sku": "T12-AGL",
    "name": "Fechadura Digital T12 Bluetooth Chave Senha Preto Agl",
    "quantity": 1.0,
    "revenue": 959.4,
    "quantity_rank": 131,
    "value_rank": 59,
    "abc_class": "C",
    "avg_price": 959.4,
    "unit_cost": 550.0,
    "stock": 0.0,
    "gross_profit": 409.4,
    "gross_margin_percent": 42.67,
    "roi10_max_cpa_total_period": 40.94,
    "category": "outros",
    "ads_score": 5.28
  },
  {
    "sku": "JVCDPA33",
    "name": "Vaso Decor Planta Cilin Decore 33 (16l) Preto ardosia Japi",
    "quantity": 2.0,
    "revenue": 573.64,
    "quantity_rank": 95,
    "value_rank": 70,
    "abc_class": "C",
    "avg_price": 286.82,
    "unit_cost": 155.0,
    "stock": 0.0,
    "gross_profit": 263.64,
    "gross_margin_percent": 45.96,
    "roi10_max_cpa_total_period": 26.36,
    "category": "vasos",
    "ads_score": 5.27
  },
  {
    "sku": "SABATINI",
    "name": "Astra, Assento Sanitário Almofadado - sabatini",
    "quantity": 12.0,
    "revenue": 1590.65,
    "quantity_rank": 113,
    "value_rank": 110,
    "abc_class": "B",
    "avg_price": 132.55,
    "unit_cost": 93.82,
    "stock": 0.0,
    "gross_profit": 464.81,
    "gross_margin_percent": 29.22,
    "roi10_max_cpa_total_period": 46.48,
    "category": "assentos",
    "ads_score": 5.11
  },
  {
    "sku": "JVCDCQ33",
    "name": "Vaso Decor Plantas Cilin Decore 33 (16l) Cimento Queim Japi",
    "quantity": 2.0,
    "revenue": 535.69,
    "quantity_rank": 101,
    "value_rank": 74,
    "abc_class": "C",
    "avg_price": 267.85,
    "unit_cost": 155.0,
    "stock": 0.0,
    "gross_profit": 225.69,
    "gross_margin_percent": 42.13,
    "roi10_max_cpa_total_period": 22.57,
    "category": "vasos",
    "ads_score": 4.85
  },
  {
    "sku": "PAPELEIRA-ADESIVA-ASTRA-BRANCA",
    "name": "Papeleira com Adesivo Branca Astra",
    "quantity": 2.0,
    "revenue": 80.46,
    "quantity_rank": 94,
    "value_rank": 119,
    "abc_class": "C",
    "avg_price": 40.23,
    "unit_cost": 23.0,
    "stock": 0.0,
    "gross_profit": 34.46,
    "gross_margin_percent": 42.83,
    "roi10_max_cpa_total_period": 3.45,
    "category": "outros",
    "ads_score": 4.46
  },
  {
    "sku": "1C7Q-LKVY-TGBG",
    "name": "Chave Soquete Tipo T 13mm Aquatools",
    "quantity": 1.0,
    "revenue": 35.0,
    "quantity_rank": 137,
    "value_rank": 135,
    "abc_class": "C",
    "avg_price": 35.0,
    "unit_cost": 9.46,
    "stock": 0.0,
    "gross_profit": 25.54,
    "gross_margin_percent": 72.97,
    "roi10_max_cpa_total_period": 2.55,
    "category": "outros",
    "ads_score": 4.38
  },
  {
    "sku": "1C7Q-LKVS-MDOC",
    "name": "Rodizio de Gel Giratório com freio 75mm rolamento Soprano",
    "quantity": 34.0,
    "revenue": 654.4,
    "quantity_rank": 13,
    "value_rank": 65,
    "abc_class": "A",
    "avg_price": 19.25,
    "unit_cost": 10.0,
    "stock": 0.0,
    "gross_profit": 314.4,
    "gross_margin_percent": 48.04,
    "roi10_max_cpa_total_period": 31.44,
    "category": "rodizios",
    "ads_score": 4.16
  },
  {
    "sku": "VED90UN",
    "name": "Rodo Vedante Borracha Friso Porta Aluminio 90 Cm Vivaliz",
    "quantity": 15.0,
    "revenue": 376.0,
    "quantity_rank": 68,
    "value_rank": 114,
    "abc_class": "A",
    "avg_price": 25.07,
    "unit_cost": 10.0,
    "stock": 0.0,
    "gross_profit": 226.0,
    "gross_margin_percent": 60.11,
    "roi10_max_cpa_total_period": 22.6,
    "category": "vedantes",
    "ads_score": 4.14
  },
  {
    "sku": "1C7Q-LKVY-UH7N",
    "name": "Chave Soquete Tipo T 10mm Hexagonal 25cm Aquatools",
    "quantity": 1.0,
    "revenue": 37.7,
    "quantity_rank": 133,
    "value_rank": 133,
    "abc_class": "C",
    "avg_price": 37.7,
    "unit_cost": 11.3,
    "stock": 0.0,
    "gross_profit": 26.4,
    "gross_margin_percent": 70.03,
    "roi10_max_cpa_total_period": 2.64,
    "category": "outros",
    "ads_score": 4.09
  },
  {
    "sku": "CSD830FBA",
    "name": "Chave Liga/desliga/liga Margirius Csd-830 30a por Alavanca",
    "quantity": 1.0,
    "revenue": 124.36,
    "quantity_rank": 138,
    "value_rank": 111,
    "abc_class": "C",
    "avg_price": 124.36,
    "unit_cost": 80.0,
    "stock": 0.0,
    "gross_profit": 44.36,
    "gross_margin_percent": 35.67,
    "roi10_max_cpa_total_period": 4.44,
    "category": "outros",
    "ads_score": 3.74
  },
  {
    "sku": "PCT-500",
    "name": "Pote Plástico 500ml Totalplast 24 Unidade Microondas Freezer",
    "quantity": 26.0,
    "revenue": 665.16,
    "quantity_rank": 18,
    "value_rank": 64,
    "abc_class": "A",
    "avg_price": 25.58,
    "unit_cost": 13.4,
    "stock": 0.0,
    "gross_profit": 316.76,
    "gross_margin_percent": 47.62,
    "roi10_max_cpa_total_period": 31.68,
    "category": "outros",
    "ads_score": 3.73
  },
  {
    "sku": "VASOPLANTASJAPI",
    "name": "Vaso Plantas Decorativo Japi Unique 16 14x16cm Preto",
    "quantity": 1.0,
    "revenue": 20.8,
    "quantity_rank": 145,
    "value_rank": 145,
    "abc_class": "C",
    "avg_price": 20.8,
    "unit_cost": 7.0,
    "stock": 0.0,
    "gross_profit": 13.8,
    "gross_margin_percent": 66.35,
    "roi10_max_cpa_total_period": 1.38,
    "category": "vasos",
    "ads_score": 3.71
  },
  {
    "sku": "VED-70",
    "name": "Rodo Vedante Borracha Friso Porta Aluminio 70cm Vivaliz",
    "quantity": 9.0,
    "revenue": 222.9,
    "quantity_rank": 117,
    "value_rank": 139,
    "abc_class": "B",
    "avg_price": 24.77,
    "unit_cost": 10.0,
    "stock": 0.0,
    "gross_profit": 132.9,
    "gross_margin_percent": 59.62,
    "roi10_max_cpa_total_period": 13.29,
    "category": "vedantes",
    "ads_score": 3.64
  },
  {
    "sku": "V0210685",
    "name": "Massa para Calafetar Madeira F12 Ipe 400g Viapol",
    "quantity": 6.0,
    "revenue": 145.25,
    "quantity_rank": 56,
    "value_rank": 105,
    "abc_class": "B",
    "avg_price": 24.21,
    "unit_cost": 9.47,
    "stock": 0.0,
    "gross_profit": 88.43,
    "gross_margin_percent": 60.88,
    "roi10_max_cpa_total_period": 8.84,
    "category": "outros",
    "ads_score": 3.53
  },
  {
    "sku": "V0210680",
    "name": "Massa Paramadeira F-12 400G/0,225L Sucupira - Viapol",
    "quantity": 7.0,
    "revenue": 174.28,
    "quantity_rank": 52,
    "value_rank": 102,
    "abc_class": "B",
    "avg_price": 24.9,
    "unit_cost": 10.0,
    "stock": 0.0,
    "gross_profit": 104.28,
    "gross_margin_percent": 59.83,
    "roi10_max_cpa_total_period": 10.43,
    "category": "outros",
    "ads_score": 3.51
  },
  {
    "sku": "REGUA5TOMADA",
    "name": "Tomada Barra Multipla Régua extensão 20A Quintupla CINZA",
    "quantity": 1.0,
    "revenue": 36.62,
    "quantity_rank": 142,
    "value_rank": 134,
    "abc_class": "C",
    "avg_price": 36.62,
    "unit_cost": 13.33,
    "stock": 0.0,
    "gross_profit": 23.29,
    "gross_margin_percent": 63.6,
    "roi10_max_cpa_total_period": 2.33,
    "category": "outros",
    "ads_score": 3.45
  },
  {
    "sku": "C06BR",
    "name": "Carrinho Fechado Ferramentas C06 3 Gavetas Branco Fercar",
    "quantity": 3.0,
    "revenue": 3273.34,
    "quantity_rank": 108,
    "value_rank": 32,
    "abc_class": "B",
    "avg_price": 1091.11,
    "unit_cost": 0.0,
    "stock": 0.0,
    "gross_profit": 0.0,
    "gross_margin_percent": 0.0,
    "roi10_max_cpa_total_period": 0.0,
    "category": "ferramentas",
    "ads_score": 3.42
  },
  {
    "sku": "V0210636",
    "name": "Massa F12 para Calafetar Madeira 400g Imbuia Viapol",
    "quantity": 8.0,
    "revenue": 193.89,
    "quantity_rank": 43,
    "value_rank": 98,
    "abc_class": "B",
    "avg_price": 24.24,
    "unit_cost": 10.14,
    "stock": 0.0,
    "gross_profit": 112.77,
    "gross_margin_percent": 58.16,
    "roi10_max_cpa_total_period": 11.28,
    "category": "outros",
    "ads_score": 3.41
  },
  {
    "sku": "JATOBADBA",
    "name": "Massa F12 para Calafetar Madeira 400g Jatoba Viapol",
    "quantity": 7.0,
    "revenue": 174.3,
    "quantity_rank": 90,
    "value_rank": 130,
    "abc_class": "B",
    "avg_price": 24.9,
    "unit_cost": 10.51,
    "stock": 0.0,
    "gross_profit": 100.73,
    "gross_margin_percent": 57.79,
    "roi10_max_cpa_total_period": 10.07,
    "category": "outros",
    "ads_score": 3.3
  },
  {
    "sku": "1C7Q-LKWA-VXHL",
    "name": "Abraçadeira Fita Perfurada",
    "quantity": 1.0,
    "revenue": 39.0,
    "quantity_rank": 127,
    "value_rank": 131,
    "abc_class": "C",
    "avg_price": 39.0,
    "unit_cost": 15.0,
    "stock": 0.0,
    "gross_profit": 24.0,
    "gross_margin_percent": 61.54,
    "roi10_max_cpa_total_period": 2.4,
    "category": "outros",
    "ads_score": 3.24
  },
  {
    "sku": "V0210643",
    "name": "Massa para Madeira F12 400g Cumaru Viapol",
    "quantity": 2.0,
    "revenue": 49.8,
    "quantity_rank": 105,
    "value_rank": 126,
    "abc_class": "C",
    "avg_price": 24.9,
    "unit_cost": 10.0,
    "stock": 0.0,
    "gross_profit": 29.8,
    "gross_margin_percent": 59.84,
    "roi10_max_cpa_total_period": 2.98,
    "category": "outros",
    "ads_score": 3.13
  },
  {
    "sku": "350X8C",
    "name": "Camara  ar 3,5 X 8 Colson",
    "quantity": 2.0,
    "revenue": 65.16,
    "quantity_rank": 110,
    "value_rank": 123,
    "abc_class": "C",
    "avg_price": 32.58,
    "unit_cost": 13.15,
    "stock": 0.0,
    "gross_profit": 38.86,
    "gross_margin_percent": 59.64,
    "roi10_max_cpa_total_period": 3.89,
    "category": "outros",
    "ads_score": 3.13
  },
  {
    "sku": "V0210675",
    "name": "Massa F12 para Calafetar Madeira 400g Cerejeira Viapol",
    "quantity": 3.0,
    "revenue": 72.7,
    "quantity_rank": 83,
    "value_rank": 121,
    "abc_class": "C",
    "avg_price": 24.23,
    "unit_cost": 10.51,
    "stock": 0.0,
    "gross_profit": 41.17,
    "gross_margin_percent": 56.63,
    "roi10_max_cpa_total_period": 4.12,
    "category": "outros",
    "ads_score": 2.89
  },
  {
    "sku": "CASTANHODBA",
    "name": "Massa F12 para Calafetar Madeira 400g Castanho Viapol",
    "quantity": 5.0,
    "revenue": 112.2,
    "quantity_rank": 67,
    "value_rank": 113,
    "abc_class": "B",
    "avg_price": 22.44,
    "unit_cost": 10.37,
    "stock": 0.0,
    "gross_profit": 60.35,
    "gross_margin_percent": 53.79,
    "roi10_max_cpa_total_period": 6.04,
    "category": "outros",
    "ads_score": 2.74
  },
  {
    "sku": "V0217760",
    "name": "Massa Paramadeira F-12 400G/0,225L Angelim - Viapol",
    "quantity": 3.0,
    "revenue": 66.0,
    "quantity_rank": 84,
    "value_rank": 122,
    "abc_class": "C",
    "avg_price": 22.0,
    "unit_cost": 10.0,
    "stock": 0.0,
    "gross_profit": 36.0,
    "gross_margin_percent": 54.55,
    "roi10_max_cpa_total_period": 3.6,
    "category": "outros",
    "ads_score": 2.67
  },
  {
    "sku": "1C7Q-LKVS-MQQN",
    "name": "Rodizio de Gel Giratório Sem Freio 75mm Rolamento Soprano",
    "quantity": 14.0,
    "revenue": 258.16,
    "quantity_rank": 31,
    "value_rank": 86,
    "abc_class": "A",
    "avg_price": 18.44,
    "unit_cost": 10.0,
    "stock": 0.0,
    "gross_profit": 118.16,
    "gross_margin_percent": 45.77,
    "roi10_max_cpa_total_period": 11.82,
    "category": "rodizios",
    "ads_score": 2.54
  },
  {
    "sku": "JVAQCQ55",
    "name": "Vaso Decorativo Plantas Antique 55 (75l) Cimento Queim Japi",
    "quantity": 5.0,
    "revenue": 2156.97,
    "quantity_rank": 66,
    "value_rank": 35,
    "abc_class": "B",
    "avg_price": 431.39,
    "unit_cost": 0.0,
    "stock": 0.0,
    "gross_profit": 0.0,
    "gross_margin_percent": 0.0,
    "roi10_max_cpa_total_period": 0.0,
    "category": "vasos",
    "ads_score": 2.41
  },
  {
    "sku": "21049",
    "name": "Resistencia 3 Temperaturas 127v 5400w Enerducha Plus Up Pratimix",
    "quantity": 1.0,
    "revenue": 33.74,
    "quantity_rank": 135,
    "value_rank": 136,
    "abc_class": "C",
    "avg_price": 33.74,
    "unit_cost": 16.0,
    "stock": 0.0,
    "gross_profit": 17.74,
    "gross_margin_percent": 52.58,
    "roi10_max_cpa_total_period": 1.77,
    "category": "outros",
    "ads_score": 2.34
  },
  {
    "sku": "V0210691",
    "name": "Massa F12 para Calafetar Madeira 400g Mogno Viapol",
    "quantity": 1.0,
    "revenue": 22.44,
    "quantity_rank": 139,
    "value_rank": 143,
    "abc_class": "C",
    "avg_price": 22.44,
    "unit_cost": 11.22,
    "stock": 0.0,
    "gross_profit": 11.22,
    "gross_margin_percent": 50.0,
    "roi10_max_cpa_total_period": 1.12,
    "category": "outros",
    "ads_score": 2.07
  },
  {
    "sku": "PARAFUSO5X16",
    "name": "Parafuso 5x16",
    "quantity": 96.0,
    "revenue": 0.0,
    "quantity_rank": 6,
    "value_rank": 146,
    "abc_class": "A",
    "avg_price": 0.0,
    "unit_cost": 0.1,
    "stock": 0.0,
    "gross_profit": -9.6,
    "gross_margin_percent": 0.0,
    "roi10_max_cpa_total_period": 0.0,
    "category": "outros",
    "ads_score": 1.8
  },
  {
    "sku": "TVT/K-NOVO-2",
    "name": "Assento Sanitário Almofadado Avant/Fit/Versato/Angra Branco Astra",
    "quantity": 9.0,
    "revenue": 1215.0,
    "quantity_rank": 38,
    "value_rank": 53,
    "abc_class": "B",
    "avg_price": 135.0,
    "unit_cost": 0.0,
    "stock": 0.0,
    "gross_profit": 0.0,
    "gross_margin_percent": 0.0,
    "roi10_max_cpa_total_period": 0.0,
    "category": "assentos",
    "ads_score": 1.67
  },
  {
    "sku": "06",
    "name": "Caixa Ferramentas Sanfonada 5 Gavetas 40x20x21 Cm N06 Fercar",
    "quantity": 8.0,
    "revenue": 1223.84,
    "quantity_rank": 44,
    "value_rank": 52,
    "abc_class": "B",
    "avg_price": 152.98,
    "unit_cost": 0.0,
    "stock": 0.0,
    "gross_profit": 0.0,
    "gross_margin_percent": 0.0,
    "roi10_max_cpa_total_period": 0.0,
    "category": "ferramentas",
    "ads_score": 1.62
  },
  {
    "sku": "JVAQCQ56",
    "name": "Vaso Decorativo Plantas Antique 56 (46l) Cimento Queim Japi",
    "quantity": 4.0,
    "revenue": 1055.88,
    "quantity_rank": 76,
    "value_rank": 58,
    "abc_class": "B",
    "avg_price": 263.97,
    "unit_cost": 0.0,
    "stock": 0.0,
    "gross_profit": 0.0,
    "gross_margin_percent": 0.0,
    "roi10_max_cpa_total_period": 0.0,
    "category": "vasos",
    "ads_score": 1.26
  },
  {
    "sku": "TVT-THEMA",
    "name": "Assento Almofadado Thema Incepa/hawaii Branco Astra",
    "quantity": 6.0,
    "revenue": 779.4,
    "quantity_rank": 54,
    "value_rank": 61,
    "abc_class": "B",
    "avg_price": 129.9,
    "unit_cost": 0.0,
    "stock": 0.0,
    "gross_profit": 0.0,
    "gross_margin_percent": 0.0,
    "roi10_max_cpa_total_period": 0.0,
    "category": "assentos",
    "ads_score": 1.08
  },
  {
    "sku": "TVT/K",
    "name": "Assento Almofadado Branco Astra para Sanitários Avant/fit/versato/angra Astra",
    "quantity": 4.0,
    "revenue": 568.0,
    "quantity_rank": 70,
    "value_rank": 73,
    "abc_class": "B",
    "avg_price": 142.0,
    "unit_cost": 0.0,
    "stock": 0.0,
    "gross_profit": 0.0,
    "gross_margin_percent": 0.0,
    "roi10_max_cpa_total_period": 0.0,
    "category": "assentos",
    "ads_score": 0.77
  },
  {
    "sku": "JVAQAC56",
    "name": "Vaso Decorativo Plantas Antique 56 (46l) Aco Corten Japi",
    "quantity": 2.0,
    "revenue": 601.69,
    "quantity_rank": 109,
    "value_rank": 69,
    "abc_class": "C",
    "avg_price": 300.85,
    "unit_cost": 0.0,
    "stock": 0.0,
    "gross_profit": 0.0,
    "gross_margin_percent": 0.0,
    "roi10_max_cpa_total_period": 0.0,
    "category": "vasos",
    "ads_score": 0.7
  },
  {
    "sku": "AD/PS*BR",
    "name": "Suporte Shampoo Prateleiras Banheiro Sem Furo Astra Branco",
    "quantity": 5.0,
    "revenue": 316.4,
    "quantity_rank": 118,
    "value_rank": 124,
    "abc_class": "B",
    "avg_price": 63.28,
    "unit_cost": 0.0,
    "stock": 0.0,
    "gross_profit": 0.0,
    "gross_margin_percent": 0.0,
    "roi10_max_cpa_total_period": 0.0,
    "category": "outros",
    "ads_score": 0.57
  },
  {
    "sku": "02",
    "name": "Caixa Ferramentas Bau Reto N02 40x16x15 Cm Bandeja Fercar",
    "quantity": 3.0,
    "revenue": 221.1,
    "quantity_rank": 78,
    "value_rank": 94,
    "abc_class": "B",
    "avg_price": 73.7,
    "unit_cost": 0.0,
    "stock": 0.0,
    "gross_profit": 0.0,
    "gross_margin_percent": 0.0,
    "roi10_max_cpa_total_period": 0.0,
    "category": "ferramentas",
    "ads_score": 0.37
  },
  {
    "sku": "A6-PSZ7-0HCS",
    "name": "Japi Floreira Flat Cachepot 57 Chumbo 6L - JFQFE57 - Uso Interno e Externo - Cantos Retos - Garantia 10 Anos",
    "quantity": 2.0,
    "revenue": 258.0,
    "quantity_rank": 91,
    "value_rank": 87,
    "abc_class": "C",
    "avg_price": 129.0,
    "unit_cost": 0.0,
    "stock": 0.0,
    "gross_profit": 0.0,
    "gross_margin_percent": 0.0,
    "roi10_max_cpa_total_period": 0.0,
    "category": "vasos",
    "ads_score": 0.36
  },
  {
    "sku": "04",
    "name": "Caixa Ferramentas Sanfonada 3 Gavetas 40x20x17 Cm N04 Fercar",
    "quantity": 2.0,
    "revenue": 231.1,
    "quantity_rank": 104,
    "value_rank": 90,
    "abc_class": "C",
    "avg_price": 115.55,
    "unit_cost": 0.0,
    "stock": 0.0,
    "gross_profit": 0.0,
    "gross_margin_percent": 0.0,
    "roi10_max_cpa_total_period": 0.0,
    "category": "ferramentas",
    "ads_score": 0.33
  },
  {
    "sku": "F12BRANCAFBA",
    "name": "Padrão",
    "quantity": 3.0,
    "revenue": 152.93,
    "quantity_rank": 85,
    "value_rank": 104,
    "abc_class": "C",
    "avg_price": 50.98,
    "unit_cost": 0.0,
    "stock": 0.0,
    "gross_profit": 0.0,
    "gross_margin_percent": 0.0,
    "roi10_max_cpa_total_period": 0.0,
    "category": "outros",
    "ads_score": 0.3
  },
  {
    "sku": "1C7Q-LKV8-WWYY",
    "name": "Assento Pp Plus Soft Close Suite Branco 3379880010100 Incepa",
    "quantity": 1.0,
    "revenue": 228.02,
    "quantity_rank": 116,
    "value_rank": 92,
    "abc_class": "C",
    "avg_price": 228.02,
    "unit_cost": 0.0,
    "stock": 0.0,
    "gross_profit": 0.0,
    "gross_margin_percent": 0.0,
    "roi10_max_cpa_total_period": 0.0,
    "category": "assentos",
    "ads_score": 0.28
  },
  {
    "sku": "D5-DKK7-TVWT",
    "name": "Floreira FLAT 57 Preto Ardosia",
    "quantity": 1.0,
    "revenue": 154.08,
    "quantity_rank": 143,
    "value_rank": 103,
    "abc_class": "C",
    "avg_price": 154.08,
    "unit_cost": 0.0,
    "stock": 0.0,
    "gross_profit": 0.0,
    "gross_margin_percent": 0.0,
    "roi10_max_cpa_total_period": 0.0,
    "category": "vasos",
    "ads_score": 0.2
  },
  {
    "sku": "PET/CAE-RSP",
    "name": "Astra Pet, Caixa De Areia 46,5x36x11,7cm Pet Cães Gatos Rosa",
    "quantity": 2.0,
    "revenue": 87.99,
    "quantity_rank": 89,
    "value_rank": 117,
    "abc_class": "C",
    "avg_price": 43.99,
    "unit_cost": 0.0,
    "stock": 0.0,
    "gross_profit": 0.0,
    "gross_margin_percent": 0.0,
    "roi10_max_cpa_total_period": 0.0,
    "category": "outros",
    "ads_score": 0.19
  },
  {
    "sku": "TVT-K",
    "name": "Assento Almofadado Avant/Fit/Versato/Angra Branco Astra Branco",
    "quantity": 1.0,
    "revenue": 137.61,
    "quantity_rank": 125,
    "value_rank": 106,
    "abc_class": "C",
    "avg_price": 137.61,
    "unit_cost": 0.0,
    "stock": 0.0,
    "gross_profit": 0.0,
    "gross_margin_percent": 0.0,
    "roi10_max_cpa_total_period": 0.0,
    "category": "assentos",
    "ads_score": 0.19
  },
  {
    "sku": "MLB3553650977",
    "name": "Ducha Chuveirão Cascata Alumínio Capelacqua 6 Polegadas",
    "quantity": 1.0,
    "revenue": 135.82,
    "quantity_rank": 129,
    "value_rank": 107,
    "abc_class": "C",
    "avg_price": 135.82,
    "unit_cost": 0.0,
    "stock": 0.0,
    "gross_profit": 0.0,
    "gross_margin_percent": 0.0,
    "roi10_max_cpa_total_period": 0.0,
    "category": "outros",
    "ads_score": 0.19
  },
  {
    "sku": "1C7Q-LKUB-0PQX",
    "name": "Astra, Assento Sanitário Almofadado Thema Branco 01",
    "quantity": 1.0,
    "revenue": 129.9,
    "quantity_rank": 115,
    "value_rank": 108,
    "abc_class": "C",
    "avg_price": 129.9,
    "unit_cost": 0.0,
    "stock": 0.0,
    "gross_profit": 0.0,
    "gross_margin_percent": 0.0,
    "roi10_max_cpa_total_period": 0.0,
    "category": "assentos",
    "ads_score": 0.18
  },
  {
    "sku": "16979",
    "name": "Caixa Organizadora 12 Gavetas  Parafusos Laranja Aquatools",
    "quantity": 1.0,
    "revenue": 127.42,
    "quantity_rank": 124,
    "value_rank": 109,
    "abc_class": "C",
    "avg_price": 127.42,
    "unit_cost": 0.0,
    "stock": 0.0,
    "gross_profit": 0.0,
    "gross_margin_percent": 0.0,
    "roi10_max_cpa_total_period": 0.0,
    "category": "outros",
    "ads_score": 0.18
  },
  {
    "sku": "80CM",
    "name": "Kit 2 Vedantes Para Porta de Alumínio e Borracha Laminada 80/90/100 cm Veda Agua e Insetos - 80cm",
    "quantity": 1.0,
    "revenue": 45.9,
    "quantity_rank": 120,
    "value_rank": 128,
    "abc_class": "C",
    "avg_price": 45.9,
    "unit_cost": 0.0,
    "stock": 0.0,
    "gross_profit": 0.0,
    "gross_margin_percent": 0.0,
    "roi10_max_cpa_total_period": 0.0,
    "category": "vedantes",
    "ads_score": 0.1
  },
  {
    "sku": "CXDESFBA",
    "name": "Caixa de Descarga Elevada Branca com Volume Regulável de 6,8L a 9L Astra",
    "quantity": 1.0,
    "revenue": 47.9,
    "quantity_rank": 128,
    "value_rank": 127,
    "abc_class": "C",
    "avg_price": 47.9,
    "unit_cost": 0.0,
    "stock": 0.0,
    "gross_profit": 0.0,
    "gross_margin_percent": 0.0,
    "roi10_max_cpa_total_period": 0.0,
    "category": "outros",
    "ads_score": 0.1
  },
  {
    "sku": "KIT-VEDANT-100",
    "name": "Aquatools Kit 2 Vedantes Porta Rodo Vedador 70/80/90/100cm Alumínio",
    "quantity": 1.0,
    "revenue": 45.0,
    "quantity_rank": 141,
    "value_rank": 129,
    "abc_class": "C",
    "avg_price": 45.0,
    "unit_cost": 0.0,
    "stock": 0.0,
    "gross_profit": 0.0,
    "gross_margin_percent": 0.0,
    "roi10_max_cpa_total_period": 0.0,
    "category": "vedantes",
    "ads_score": 0.1
  },
  {
    "sku": "8M-MFX2-3HRZ",
    "name": "Astra TPJ/AS*BR1 Assento Sanitário Soft, Branco",
    "quantity": 8.0,
    "revenue": 288.2,
    "quantity_rank": 41,
    "value_rank": 85,
    "abc_class": "B",
    "avg_price": 36.02,
    "unit_cost": 0.0,
    "stock": 0.0,
    "gross_profit": 0.0,
    "gross_margin_percent": 0.0,
    "roi10_max_cpa_total_period": 0.0,
    "category": "assentos",
    "ads_score": -2.31
  },
  {
    "sku": "1C7Q-LKUT-WROG",
    "name": "Massa para Calafetar Madeira F12 Ipe 400 g Viapol com 6",
    "quantity": 4.0,
    "revenue": 97.52,
    "quantity_rank": 71,
    "value_rank": 115,
    "abc_class": "B",
    "avg_price": 24.38,
    "unit_cost": 0.0,
    "stock": 0.0,
    "gross_profit": 0.0,
    "gross_margin_percent": 0.0,
    "roi10_max_cpa_total_period": 0.0,
    "category": "outros",
    "ads_score": -2.7
  },
  {
    "sku": "SKU-343577002",
    "name": "Chave Teste 140MM 100/500V",
    "quantity": 3.0,
    "revenue": 26.7,
    "quantity_rank": 86,
    "value_rank": 138,
    "abc_class": "C",
    "avg_price": 8.9,
    "unit_cost": 0.0,
    "stock": 0.0,
    "gross_profit": 0.0,
    "gross_margin_percent": 0.0,
    "roi10_max_cpa_total_period": 0.0,
    "category": "outros",
    "ads_score": -2.82
  },
  {
    "sku": "DESEMPENADEIRA-BORRACHA-18X30-CASTOR",
    "name": "Desempenadeira Com Borracha 18cm X 30cm",
    "quantity": 2.0,
    "revenue": 57.2,
    "quantity_rank": 92,
    "value_rank": 125,
    "abc_class": "C",
    "avg_price": 28.6,
    "unit_cost": 0.0,
    "stock": 0.0,
    "gross_profit": 0.0,
    "gross_margin_percent": 0.0,
    "roi10_max_cpa_total_period": 0.0,
    "category": "outros",
    "ads_score": -2.84
  },
  {
    "sku": "QK-282I-QOIO",
    "name": "Robust Alicate Universal 8 Polegadas, Aço Forjado, Cabo Ergonômico, Uso Profissional",
    "quantity": 1.0,
    "revenue": 39.0,
    "quantity_rank": 144,
    "value_rank": 132,
    "abc_class": "C",
    "avg_price": 39.0,
    "unit_cost": 0.0,
    "stock": 0.0,
    "gross_profit": 0.0,
    "gross_margin_percent": 0.0,
    "roi10_max_cpa_total_period": 0.0,
    "category": "outros",
    "ads_score": -2.91
  },
  {
    "sku": "86617",
    "name": "Maçaneta Alavanca para Porta Aliança Cromada. 86617 Cor Inox",
    "quantity": 1.0,
    "revenue": 31.12,
    "quantity_rank": 130,
    "value_rank": 137,
    "abc_class": "C",
    "avg_price": 31.12,
    "unit_cost": 0.0,
    "stock": 0.0,
    "gross_profit": 0.0,
    "gross_margin_percent": 0.0,
    "roi10_max_cpa_total_period": 0.0,
    "category": "outros",
    "ads_score": -2.92
  },
  {
    "sku": "80",
    "name": "Vedante para Porta Rodo Vedador 80, 90 ou 100cm Aluminio - 80",
    "quantity": 1.0,
    "revenue": 23.9,
    "quantity_rank": 122,
    "value_rank": 140,
    "abc_class": "C",
    "avg_price": 23.9,
    "unit_cost": 0.0,
    "stock": 0.0,
    "gross_profit": 0.0,
    "gross_margin_percent": 0.0,
    "roi10_max_cpa_total_period": 0.0,
    "category": "vedantes",
    "ads_score": -2.93
  },
  {
    "sku": "M8-9W1Z-2EFT",
    "name": "Massa P/Madeira F-12 400G/0,225L Sucupira - Viapol",
    "quantity": 1.0,
    "revenue": 22.41,
    "quantity_rank": 134,
    "value_rank": 144,
    "abc_class": "C",
    "avg_price": 22.41,
    "unit_cost": 0.0,
    "stock": 0.0,
    "gross_profit": 0.0,
    "gross_margin_percent": 0.0,
    "roi10_max_cpa_total_period": 0.0,
    "category": "outros",
    "ads_score": -2.93
  },
  {
    "sku": "PC-MFZR-W69S",
    "name": "Massa F12 para Calafetar Madeira 400g Marfim",
    "quantity": 1.0,
    "revenue": 23.43,
    "quantity_rank": 136,
    "value_rank": 141,
    "abc_class": "C",
    "avg_price": 23.43,
    "unit_cost": 0.0,
    "stock": 0.0,
    "gross_profit": 0.0,
    "gross_margin_percent": 0.0,
    "roi10_max_cpa_total_period": 0.0,
    "category": "outros",
    "ads_score": -2.93
  }
]